{"id": "42606800", "premium": false, "billing_type": {"id": "standard", "name": "Стандарт"}, "relations": [], "name": "Региональный менеджер по продажам", "insider_interview": null, "response_letter_required": false, "area": {"id": "78", "name": "Самара", "url": "https://api.hh.ru/areas/78?host=hh.ru"}, "salary": {"from": 60000, "to": 100000, "currency": "RUR", "gross": false}, "type": {"id": "open", "name": "Открытая"}, "address": {"city": "Самара", "street": "проспект Кирова", "building": "69к1", "description": null, "lat": 53.202427, "lng": 50.286989, "raw": "Самара, проспект Кирова, 69к1", "metro": null, "metro_stations": []}, "allow_messages": true, "site": {"id": "hh", "name": "hh.ru"}, "experience": {"id": "between1And3", "name": "От 1 года до 3 лет"}, "schedule": {"id": "fullDay", "name": "Полный день"}, "employment": {"id": "full", "name": "Полная занятость"}, "department": null, "contacts": null, "description": "<p><strong>Обязанности</strong>:</p> <ul> <li>работа с имеющейся клиентской базой,поиск новых клиентов</li> <li>планирование продаж,анализ рынка сбыта и конкурентной среды</li> <li>продвижение собственных брендов компании.</li> <li>работа и система отчетности в СRM- системе, 1С8-торговля, Битрикс 24</li> <li>контроль дебиторской задолженности</li> <li>командировки по зоне ответственности</li> </ul> <p><br /><strong>Требования</strong>:</p> <ul> <li>опыт работы в продажах.</li> <li>умение вести переговоры.</li> <li>целеустремленность.</li> <li>самостоятельность.</li> <li>желание расти профессионально,зарабатывать.</li> <li>умение достигать поставленных целей.</li> <li>готовность к командировкам</li> </ul> <p><br /><strong>Условия</strong>:</p> <ul> <li>работа в команде.</li> <li>компенсация питания.</li> <li>полный соцпакет, оформление по ТК.</li> <li>работа в стабильной (25 лет на рынке) мультибрендовой компании, одним из лидеров на рынке инженерной сантехники.</li> </ul>", "branded_description": null, "vacancy_constructor_template": null, "key_skills": [], "accept_handicapped": false, "accept_kids": false, "archived": false, "response_url": null, "specializations": [{"id": "17.417", "name": "Строительные материалы", "profarea_id": "17", "profarea_name": "Продажи"}, {"id": "17.196", "name": "Оптовая торговля", "profarea_id": "17", "profarea_name": "Продажи"}, {"id": "17.324", "name": "Управление продажами", "profarea_id": "17", "profarea_name": "Продажи"}, {"id": "17.486", "name": "Сантехника", "profarea_id": "17", "profarea_name": "Продажи"}], "code": null, "hidden": false, "quick_responses_allowed": false, "driver_license_types": [], "accept_incomplete_resumes": false, "employer": "1148183", "published_at": "2021-04-17T11:49:10+0300", "created_at": "2021-04-17T11:49:10+0300", "negotiations_url": null, "suitable_resumes_url": null, "apply_alternate_url": "https://hh.ru/applicant/vacancy_response?vacancyId=42606800", "has_test": false, "test": null, "alternate_url": "https://hh.ru/vacancy/42606800", "working_days": [], "working_time_intervals": [], "working_time_modes": [], "accept_temporary": false, "name_vac": "Менеджер"}