{"id": "43862902", "premium": false, "billing_type": {"id": "standard", "name": "Стандарт"}, "relations": [], "name": "Инженер ПТО (г. Нерюнгри, г. Иркутск)", "insider_interview": null, "response_letter_required": false, "area": {"id": "78", "name": "Самара", "url": "https://api.hh.ru/areas/78?host=hh.ru"}, "salary": {"from": 90000, "to": 120000, "currency": "RUR", "gross": false}, "type": {"id": "open", "name": "Открытая"}, "address": null, "allow_messages": true, "site": {"id": "hh", "name": "hh.ru"}, "experience": {"id": "between1And3", "name": "От 1 года до 3 лет"}, "schedule": {"id": "flyInFlyOut", "name": "Вахтовый метод"}, "employment": {"id": "full", "name": "Полная занятость"}, "department": null, "contacts": null, "description": "<p><em><strong>Для работы на крупном газо-строительном объектах, на постоянную основу требуется инженер ПТО.</strong></em></p> <p><strong>Условия:</strong></p> <ul> <li>Официальное трудоустройство, согласно ТК РФ,</li> <li>Своевременная заработная &quot;белая&quot; плата (2 раза в месяц),</li> <li>За счет работодателя предоставляется авиаперелет + комфортабельное модульное проживание в вахтовом поселке за счет работодателя + питание в столовой (трехразовое питание).</li> <li><strong>Вахтовый метод работы в местности с особыми климатическими условиями, график 60 дней (включая 14 дней обсервации)/37 дней отдых.</strong></li> </ul> <p><strong>Обязанности:</strong></p> <ul> <li>Проверка качества проектно-сметной документации с оформлением замечаний, разработка ППР, техкарты, ведение и подписание исполнительной документации, оформление входного контроля поступающих материалов, ведение общих журналов, согласование отступления от проектов с авторским надзором.</li> </ul> <p><strong>Требования:</strong></p> <ul> <li>знание ПК, образование высшее, среднее профессиональное</li> <li>опыт работы по строительству объектов нефтяной , газовой промышленности ОБЯЗАТЕЛЕН не менее 2 лет.</li> </ul>", "branded_description": null, "vacancy_constructor_template": null, "key_skills": [{"name": "AutoCAD"}, {"name": "Гранд-смета"}, {"name": "Строительство"}, {"name": "Проектная документация"}, {"name": "Строительный контроль"}], "accept_handicapped": false, "accept_kids": false, "archived": false, "response_url": null, "specializations": [{"id": "20.287", "name": "Строительство", "profarea_id": "20", "profarea_name": "Строительство, недвижимость"}, {"id": "20.387", "name": "Прораб", "profarea_id": "20", "profarea_name": "Строительство, недвижимость"}], "code": null, "hidden": false, "quick_responses_allowed": false, "driver_license_types": [], "accept_incomplete_resumes": false, "employer": "3112659", "published_at": "2021-04-14T07:10:34+0300", "created_at": "2021-04-14T07:10:34+0300", "negotiations_url": null, "suitable_resumes_url": null, "apply_alternate_url": "https://hh.ru/applicant/vacancy_response?vacancyId=43862902", "has_test": false, "test": null, "alternate_url": "https://hh.ru/vacancy/43862902", "working_days": [], "working_time_intervals": [], "working_time_modes": [], "accept_temporary": false, "name_vac": "Инженер"}