{"id": "43913886", "premium": false, "billing_type": {"id": "standard", "name": "Стандарт"}, "relations": [], "name": "Менеджер по выдаче займов (Самара)", "insider_interview": null, "response_letter_required": false, "area": {"id": "78", "name": "Самара", "url": "https://api.hh.ru/areas/78?host=hh.ru"}, "salary": {"from": 30000, "to": 40000, "currency": "RUR", "gross": false}, "type": {"id": "open", "name": "Открытая"}, "address": {"city": "Самара", "street": "проспект Кирова", "building": "226Б", "description": null, "lat": 53.243481, "lng": 50.231464, "raw": "Самара, проспект Кирова, 226Б", "metro": null, "metro_stations": []}, "allow_messages": true, "site": {"id": "hh", "name": "hh.ru"}, "experience": {"id": "between1And3", "name": "От 1 года до 3 лет"}, "schedule": {"id": "shift", "name": "Сменный график"}, "employment": {"id": "full", "name": "Полная занятость"}, "department": null, "contacts": null, "description": "<p>Требуемый опыт работы: 1-3 года</p> <p>Полная занятость, сменный график</p> <p>Компания &quot;Положительное решение&quot; проводит набор сотрудников, которые не боятся работать в условиях многозадачности и нацелены на результат! Наша компания открыта для энергичных и инициативных сотрудников, заинтересованных в своем развитии! Присоединяйтесь!</p> <p> </p> <p><strong>Опыт работы:</strong></p> <p> </p> <ul> <li>Опыт продаж финансовых продуктов приветствуется, так же рассматриваем кандидатов без опыта работы.</li> </ul> <p> </p> <p><strong>Что нужно делать:</strong></p> <p> </p> <ul> <li>Консультирование клиентов по вопросам предоставления займов.</li> <li>Оформление заявок, первичная проверка клиентов.</li> <li>Контроль кассы, работа с наличными, ведение документации и отчетности.</li> <li>Звонки клиентам.</li> </ul> <p> </p> <p><strong>Что мы ожидаем от кандидата:</strong></p> <p> </p> <ul> <li>Опыт работы в банках, МФО, сотовых или страховых компаниях, будет преимуществом.</li> <li>Высокие коммуникативные качества (умение найти общий язык с любым клиентом).</li> <li>Владение ПК и орг. техникой на уровне пользователя</li> <li>Дисциплинированность, вежливость, грамотная речь.</li> <li>Ответственное отношение к работе.</li> </ul> <p> </p> <p><strong>Что мы предлагаем:</strong></p> <p> </p> <ul> <li>Официальное трудоустройство по ТК РФ.</li> <li>Оплачиваемое обучение.</li> <li>Оплата больничных и отпусков.</li> <li>Стабильный доход (оклад + премия).</li> <li>Полностью официальная зарплата, понятная система мотивации.</li> <li>Еженедельные выплаты.</li> <li>Удобное расположение офиса.</li> <li>График работы сменный с 10.00 до 20.00 (2/2).</li> <li>Дружная команда.</li> </ul>", "branded_description": null, "vacancy_constructor_template": null, "key_skills": [{"name": "Ведение переговоров"}, {"name": "Поиск и привлечение клиентов"}, {"name": "Активные продажи"}, {"name": "Пользователь ПК"}, {"name": "Холодные продажи"}, {"name": "Телефонные переговоры"}, {"name": "Работа в команде"}, {"name": "Навыки продаж"}, {"name": "Холодные звонки"}, {"name": "Прямые продажи"}, {"name": "Грамотная речь"}], "accept_handicapped": false, "accept_kids": false, "archived": false, "response_url": null, "specializations": [{"id": "5.219", "name": "Привлечение клиентов", "profarea_id": "5", "profarea_name": "Банки, инвестиции, лизинг"}, {"id": "5.224", "name": "Продажа финансовых продуктов", "profarea_id": "5", "profarea_name": "Банки, инвестиции, лизинг"}, {"id": "5.177", "name": "Начальный уровень, Мало опыта", "profarea_id": "5", "profarea_name": "Банки, инвестиции, лизинг"}, {"id": "5.371", "name": "Кредиты: розничные", "profarea_id": "5", "profarea_name": "Банки, инвестиции, лизинг"}, {"id": "4.278", "name": "Сотрудник call-центра", "profarea_id": "4", "profarea_name": "Административный персонал"}, {"id": "17.538", "name": "Продажи по телефону, Телемаркетинг", "profarea_id": "17", "profarea_name": "Продажи"}], "code": null, "hidden": false, "quick_responses_allowed": false, "driver_license_types": [], "accept_incomplete_resumes": true, "employer": "2493489", "published_at": "2021-04-15T12:20:19+0300", "created_at": "2021-04-15T12:20:19+0300", "negotiations_url": null, "suitable_resumes_url": null, "apply_alternate_url": "https://hh.ru/applicant/vacancy_response?vacancyId=43913886", "has_test": false, "test": null, "alternate_url": "https://hh.ru/vacancy/43913886", "working_days": [], "working_time_intervals": [], "working_time_modes": [], "accept_temporary": false, "name_vac": "Менеджер"}