{"id": "41502382", "premium": false, "billing_type": {"id": "standard", "name": "Стандарт"}, "relations": [], "name": "Менеджер оптового отдела", "insider_interview": null, "response_letter_required": false, "area": {"id": "78", "name": "Самара", "url": "https://api.hh.ru/areas/78?host=hh.ru"}, "salary": {"from": 28500, "to": null, "currency": "RUR", "gross": true}, "type": {"id": "open", "name": "Открытая"}, "address": {"city": "Самара", "street": "проспект Юных Пионеров", "building": "146", "description": null, "lat": 53.231279, "lng": 50.258485, "raw": "Самара, проспект Юных Пионеров, 146", "metro": null, "metro_stations": []}, "allow_messages": true, "site": {"id": "hh", "name": "hh.ru"}, "experience": {"id": "between3And6", "name": "От 3 до 6 лет"}, "schedule": {"id": "fullDay", "name": "Полный день"}, "employment": {"id": "full", "name": "Полная занятость"}, "department": null, "contacts": null, "description": "<p>Книготорговая компания &quot;МЕТИДА&quot; в связи с увеличением объемов работ приглашает в команду Менеджера оптового отдела!!!</p> <p><strong>Обязанности:</strong></p> <ul> <li>Осуществлять поиск новых контрагентов</li> <li> <p>Осуществлять сбытовую деятельность в соответствии с заказами и заключенными договорами</p> </li> <li> <p>обеспечивать поставку товаров заказчикам в установленные сроки и полном объеме</p> </li> <li> <p>Вносить предложения по объемам продаж, по выбору каналов сбыта, способов и времени выхода на рынок</p> </li> <li> <p>участвовать в выездной торговле</p> </li> </ul> <strong>Требования:</strong> <ul> <li>Опыт работы в активных продажах от 5 лет</li> <li>опыт работы с канцтоварами, художественной и учебной литературой станет Вашим ОГРОМНЫМ ПРЕИМУЩЕСТВОМ!!!</li> <li>Опыт работы в 1С 8.3</li> <li>Любовь к книгам и желание расти и развиваться в книжном бизнесе</li> </ul> <strong>Условия:</strong> <ul> <li>график работы 5\\2, суббота, воскресение - выходной</li> <li>режим работы с 9.00 до 18.00</li> <li>заработная плата - фиксированный оклад + премия</li> <li>официальное трудоустройство в соответствии с ТК РФ</li> <li>скидки и льготы на услуги и продукцию Группы компаний</li> <li>встречи с интересными людьми и активная творческая жизнь - это приятный бонус)))</li> </ul>", "branded_description": null, "vacancy_constructor_template": null, "key_skills": [{"name": "1С: Торговля"}, {"name": "Административно-хозяйственная деятельность"}, {"name": "Мониторинг рынка"}, {"name": "Заключение договоров"}, {"name": "Работа в команде"}], "accept_handicapped": false, "accept_kids": false, "archived": false, "response_url": null, "specializations": [{"id": "17.242", "name": "Прямые продажи", "profarea_id": "17", "profarea_name": "Продажи"}, {"id": "17.196", "name": "Оптовая торговля", "profarea_id": "17", "profarea_name": "Продажи"}], "code": null, "hidden": false, "quick_responses_allowed": false, "driver_license_types": [], "accept_incomplete_resumes": false, "employer": "3158955", "published_at": "2021-04-13T16:32:53+0300", "created_at": "2021-04-13T16:32:53+0300", "negotiations_url": null, "suitable_resumes_url": null, "apply_alternate_url": "https://hh.ru/applicant/vacancy_response?vacancyId=41502382", "has_test": false, "test": null, "alternate_url": "https://hh.ru/vacancy/41502382", "working_days": [], "working_time_intervals": [], "working_time_modes": [], "accept_temporary": false, "name_vac": "Менеджер"}