{"id": "42884351", "premium": false, "billing_type": {"id": "standard_plus", "name": "Стандарт плюс"}, "relations": [], "name": "Инженер-строитель", "insider_interview": null, "response_letter_required": false, "area": {"id": "78", "name": "Самара", "url": "https://api.hh.ru/areas/78?host=hh.ru"}, "salary": {"from": 60000, "to": null, "currency": "RUR", "gross": false}, "type": {"id": "open", "name": "Открытая"}, "address": {"city": null, "street": null, "building": null, "description": null, "lat": 0.0, "lng": 0.0, "raw": "г. Самара, ул. Белогородская, 1", "metro": null, "metro_stations": []}, "allow_messages": true, "site": {"id": "hh", "name": "hh.ru"}, "experience": {"id": "between3And6", "name": "От 3 до 6 лет"}, "schedule": {"id": "fullDay", "name": "Полный день"}, "employment": {"id": "full", "name": "Полная занятость"}, "department": null, "contacts": null, "description": "<p><strong>Обязанности:</strong></p> <ul> <li> <p>Организация строительного производства (договоры подряда, сметы, графики работ), руководство проектом;</p> </li> <li> <p>Организация работ на строительных площадках на территории предприятия в соответствии с техническими нормами, нормами охраны труда, производственной санитарии и противопожарной защиты;</p> </li> <li> <p>Утверждение/проверка проектной документации;</p> </li> <li> <p>Подготовка исполнительной документации, необходимой для ввода объекта в эксплуатацию;</p> </li> <li> <p>Контроль выполнения планов строительства, сроков и качества СМР, а также качества применяемых материалов, изделий, конструкций;</p> </li> <li> <p>Контроль выполнения графика и обеспечения качества строительных работ;</p> </li> <li> <p>Проверка на наличие и ведение документации на объектах;</p> </li> <li> <p>Приемка выполненных работ;</p> </li> <li> <p>Закрытие финансирования по объекту (проверка объемов работ, проверка КС-2, КС-3, проведение оплат);</p> </li> <li> <p>Консультирование заказчиков по вопросам технологии строительства;</p> </li> <li> <p>Претензионная работа;</p> </li> <li> <p>Формирование еженедельных отчетов о ходе работ.</p> </li> </ul> <p><strong>Требования:</strong></p> <ul> <li> <p>Высшее профильное (строительное) образование (желательно ПГС),</p> </li> <li> <p>Отличное знание законодательства РФ в области строительства, охраны труда, нормативно-технической документации, технологий и способов ведения строительных работ;</p> </li> <li> <p>Опыт работы в аналогичной должности от 3-х лет;</p> </li> <li> <p>Умение определять физический износ зданий, несущих конструкций;</p> </li> <li> <p>Знание градостроительного кодекса;</p> </li> <li> <p>Уверенный пользование ПК (MS Office, AutoCAD, PowerPoint);</p> </li> <li> <p>Хорошие навыки общения, организаторские способности, ответственность, инициативность.</p> </li> </ul> <p><br /><strong>Условия:</strong></p> <ul> <li> <p>Оформление согласно Трудового кодекса РФ;</p> </li> <li> <p>Заработная плата от 60 000 рублей (после вычета НДФЛ-13%);</p> </li> <li> <p>Компенсация мобильной связи, ГСМ;</p> </li> <li> <p>График работы - 5/2 с 8-00 до 16-45 (выходные дни: суббота, воскресенье) на территории работодателя.</p> </li> </ul>", "branded_description": null, "vacancy_constructor_template": null, "key_skills": [{"name": "AutoCAD"}, {"name": "Строительство"}, {"name": "MS Outlook"}, {"name": "Организаторские навыки"}, {"name": "Деловое общение"}, {"name": "Гражданское строительство"}, {"name": "Подготовка презентаций"}, {"name": "Документальное сопровождение"}, {"name": "Сметы"}, {"name": "MS PowerPoint"}, {"name": "Выбор подрядных организаций"}, {"name": "Договоры подряда"}, {"name": "Умение работать в команде"}, {"name": "Строительное делопроизводство"}, {"name": "Реконструкция"}, {"name": "Управление проектами"}, {"name": "Инженерные системы"}, {"name": "Капитальный ремонт"}], "accept_handicapped": false, "accept_kids": false, "archived": false, "response_url": null, "specializations": [{"id": "20.189", "name": "Нежилые помещения", "profarea_id": "20", "profarea_name": "Строительство, недвижимость"}, {"id": "20.525", "name": "Землеустройство", "profarea_id": "20", "profarea_name": "Строительство, недвижимость"}, {"id": "20.287", "name": "Строительство", "profarea_id": "20", "profarea_name": "Строительство, недвижимость"}, {"id": "20.83", "name": "Инженер", "profarea_id": "20", "profarea_name": "Строительство, недвижимость"}, {"id": "20.325", "name": "Управление проектами", "profarea_id": "20", "profarea_name": "Строительство, недвижимость"}, {"id": "20.233", "name": "Проектирование, Архитектура", "profarea_id": "20", "profarea_name": "Строительство, недвижимость"}], "code": null, "hidden": false, "quick_responses_allowed": false, "driver_license_types": [], "accept_incomplete_resumes": false, "employer": "53707", "published_at": "2021-03-30T13:58:26+0300", "created_at": "2021-03-30T13:58:26+0300", "negotiations_url": null, "suitable_resumes_url": null, "apply_alternate_url": "https://hh.ru/applicant/vacancy_response?vacancyId=42884351", "has_test": false, "test": null, "alternate_url": "https://hh.ru/vacancy/42884351", "working_days": [], "working_time_intervals": [], "working_time_modes": [], "accept_temporary": false}