{"id": "43055822", "premium": false, "billing_type": {"id": "standard_plus", "name": "Стандарт плюс"}, "relations": [], "name": "Инженер-конструктор", "insider_interview": null, "response_letter_required": false, "area": {"id": "212", "name": "Тольятти", "url": "https://api.hh.ru/areas/212?host=hh.ru"}, "salary": {"from": 32000, "to": null, "currency": "RUR", "gross": true}, "type": {"id": "open", "name": "Открытая"}, "address": null, "allow_messages": true, "site": {"id": "hh", "name": "hh.ru"}, "experience": {"id": "noExperience", "name": "Нет опыта"}, "schedule": {"id": "fullDay", "name": "Полный день"}, "employment": {"id": "full", "name": "Полная занятость"}, "department": null, "contacts": null, "description": "<strong>Обязанности:</strong> <ul> <li>Разработка нестандартных элементов для кухонных гарнитуров.</li> <li>Проверка и обработка поступающих заказов.</li> <li>Работа в Базис-Мебельщик с 3D-моделями, чертежами, а также с базой в 1С.</li> <li>Создание управляющих программ для ЧПУ станков.</li> </ul> <p><strong>Требования:</strong></p> <ul> <li>Умение работать с документацией.</li> <li>Умение находить информацию.</li> <li>Внимательность.</li> <li>Высшее образование.</li> </ul> <p><strong>Плюсы в работе:</strong></p> <ul> <li>Всему научим!</li> <li>Каждый день что-то новое и интересное!</li> <li>Большой и дружный коллектив!</li> </ul> <strong>Условия:</strong> <ul> <li>Оформление по ТК РФ.</li> <li>Работа с 8:00 до 16:45.</li> <li>Доставка по Автозаводскому р-ну.</li> </ul>", "branded_description": null, "vacancy_constructor_template": null, "key_skills": [{"name": "Базис-Мебельщик"}, {"name": "1С"}, {"name": "MS Excel"}], "accept_handicapped": false, "accept_kids": false, "archived": false, "response_url": null, "specializations": [{"id": "18.143", "name": "Мебельное производство", "profarea_id": "18", "profarea_name": "Производство, сельское хозяйство"}, {"id": "18.81", "name": "Инженер", "profarea_id": "18", "profarea_name": "Производство, сельское хозяйство"}, {"id": "18.568", "name": "Конструктор", "profarea_id": "18", "profarea_name": "Производство, сельское хозяйство"}], "code": null, "hidden": false, "quick_responses_allowed": false, "driver_license_types": [], "accept_incomplete_resumes": false, "employer": "3218200", "published_at": "2021-03-27T18:19:00+0300", "created_at": "2021-03-27T18:19:00+0300", "negotiations_url": null, "suitable_resumes_url": null, "apply_alternate_url": "https://hh.ru/applicant/vacancy_response?vacancyId=43055822", "has_test": false, "test": null, "alternate_url": "https://hh.ru/vacancy/43055822", "working_days": [], "working_time_intervals": [], "working_time_modes": [], "accept_temporary": false}