{"id": "43079332", "premium": false, "billing_type": {"id": "standard", "name": "Стандарт"}, "relations": [], "name": "Специалист по продажам (без поиска клиентов)", "insider_interview": null, "response_letter_required": false, "area": {"id": "78", "name": "Самара", "url": "https://api.hh.ru/areas/78?host=hh.ru"}, "salary": {"from": 35000, "to": null, "currency": "RUR", "gross": false}, "type": {"id": "open", "name": "Открытая"}, "address": {"city": "Самара", "street": "Аэродромная улица", "building": "45", "description": null, "lat": 53.190699, "lng": 50.187959, "raw": "Самара, Аэродромная улица, 45", "metro": null, "metro_stations": []}, "allow_messages": true, "site": {"id": "hh", "name": "hh.ru"}, "experience": {"id": "between1And3", "name": "От 1 года до 3 лет"}, "schedule": {"id": "fullDay", "name": "Полный день"}, "employment": {"id": "full", "name": "Полная занятость"}, "department": null, "contacts": null, "description": "<p>Компания &quot;Консалтика Плюс&quot; осуществляет продажи справочно-правовой системы КонсультантПлюс. Это программное обеспечение вмещающее в себя собранную структурированную законодательную базу, судебную практику с комментариями и разъяснениями, готовые рабочие решения и образцы заполнения документов.</p> <p>Наши клиенты: Юристы, Бухгалтера, Экономисты, Нотариусы, Кадровики, Закупщики, Руководители предприятий, муниципальные учреждения и банки</p> <p><strong>Обязанности:</strong></p> <ul> <li>Консультирование клиентов по продуктам и услугам компании (наш продукт справочно-правовая система КонсультантПлюс).</li> <li>Презентация и продажа услуг компании.</li> <li>Встречи с клиентами для Вас уже согласованы, вы работаете по теплой клиентской базе.</li> </ul> <strong>Требования:</strong> <ul> <li>Опыт работы в активных продажах обязателен.</li> <li>Знание MS Оffice</li> <li>Образование не ниже средне-специального</li> </ul> <strong>Условия:</strong> <ul> <li>Офисно-разъездной характер работы.</li> <li>Бесплатное профессиональное обучение на протяжении всей работы в компании (свой бизнес-тренер, обучение всем этапам работы с клиентами);</li> <li>Возможность повышать свой профессиональный уровень за счет обучения на вебинарной площадке компании по различным тематикам.</li> <li>Карьерный рост и профессиональное развитие;</li> <li>Оформление согласно ТК РФ;</li> <li>Оплата проезда, корпоративная сотовая связь;</li> <li>График работы: 5/2, с 8.00 до 17.00;</li> <li>Стабильная заработная плата (оклад 25000 + высокий процент с каждой вашей продажи). Доход не имеет потолка и зависит только от Вас.</li> <li>Корпоративные конкурсы внутри отдела с призовыми местами и ценными подарками .</li> <li>Развитая корпоративная культура.</li> <li>Мы готовы обучать и развиваться вместе с вами!</li> </ul>", "branded_description": null, "vacancy_constructor_template": null, "key_skills": [{"name": "Консультант плюс"}, {"name": "Активные продажи"}, {"name": "Холодные продажи"}, {"name": "MS PowerPoint"}, {"name": "Навыки продаж"}], "accept_handicapped": false, "accept_kids": false, "archived": false, "response_url": null, "specializations": [{"id": "12.92", "name": "Информационные технологии", "profarea_id": "12", "profarea_name": "Консультирование"}, {"id": "17.242", "name": "Прямые продажи", "profarea_id": "17", "profarea_name": "Продажи"}, {"id": "17.538", "name": "Продажи по телефону, Телемаркетинг", "profarea_id": "17", "profarea_name": "Продажи"}], "code": null, "hidden": false, "quick_responses_allowed": false, "driver_license_types": [], "accept_incomplete_resumes": false, "employer": "3961061", "published_at": "2021-04-07T09:13:07+0300", "created_at": "2021-04-07T09:13:07+0300", "negotiations_url": null, "suitable_resumes_url": null, "apply_alternate_url": "https://hh.ru/applicant/vacancy_response?vacancyId=43079332", "has_test": false, "test": null, "alternate_url": "https://hh.ru/vacancy/43079332", "working_days": [], "working_time_intervals": [], "working_time_modes": [], "accept_temporary": false, "name_vac": "Специалист"}