{"id": "43221257", "premium": false, "billing_type": {"id": "standard", "name": "Стандарт"}, "relations": [], "name": "Программист 1С", "insider_interview": null, "response_letter_required": false, "area": {"id": "78", "name": "Самара", "url": "https://api.hh.ru/areas/78?host=hh.ru"}, "salary": null, "type": {"id": "open", "name": "Открытая"}, "address": null, "allow_messages": false, "site": {"id": "hh", "name": "hh.ru"}, "experience": {"id": "between3And6", "name": "От 3 до 6 лет"}, "schedule": {"id": "fullDay", "name": "Полный день"}, "employment": {"id": "full", "name": "Полная занятость"}, "department": null, "contacts": null, "description": "<p>Компания готова рассматривать кандидатов, работающих удаленно.</p> <p>Опыт работы в компаниях с большими складами и широким ассортиментом продукции будет преимуществом.</p> <p> </p> <p><strong>Обязанности:</strong></p> <ul> <li>Сопровождение и доработка 1С ТиС под нужды предприятия;</li> <li>Переход в будущем с 1с7.7 на 1С 8;</li> <li>Автоматизация процессов; обновление типовых конфигураций 1С;</li> <li>Администрирование баз 1С 8 Бухгалтерия;</li> <li>Внедрение WMS на складе компании (желателен опыт работы с WMS системами);</li> <li>Администрирование серверов;</li> <li>Установка и настройка ПО;</li> <li>Поддержка пользователей.</li> </ul> <p><strong>Требования:</strong></p> <ul> <li>Высшее техническое образование.</li> <li>Опыт программирования в среде 1С.</li> <li>Опыт работы по внедрению WMS (как преимущество)</li> <li>Умение и желание разбираться в предметной области.</li> <li>Системный подход к проблемам.</li> </ul> <p><strong>Условия:</strong></p> <ul> <li>График работы - удаленная работа (с возможностью посещения офиса компании),</li> <li>Заработная плата по результатам собеседования</li> </ul>", "branded_description": null, "vacancy_constructor_template": null, "key_skills": [], "accept_handicapped": false, "accept_kids": false, "archived": false, "response_url": null, "specializations": [{"id": "1.221", "name": "Программирование, Разработка", "profarea_id": "1", "profarea_name": "Информационные технологии, интернет, телеком"}, {"id": "1.273", "name": "Системный администратор", "profarea_id": "1", "profarea_name": "Информационные технологии, интернет, телеком"}, {"id": "1.420", "name": "Администратор баз данных", "profarea_id": "1", "profarea_name": "Информационные технологии, интернет, телеком"}], "code": null, "hidden": false, "quick_responses_allowed": false, "driver_license_types": [], "accept_incomplete_resumes": false, "employer": "1240937", "published_at": "2021-03-22T08:39:24+0300", "created_at": "2021-03-22T08:39:24+0300", "negotiations_url": null, "suitable_resumes_url": null, "apply_alternate_url": "https://hh.ru/applicant/vacancy_response?vacancyId=43221257", "has_test": false, "test": null, "alternate_url": "https://hh.ru/vacancy/43221257", "working_days": [], "working_time_intervals": [], "working_time_modes": [], "accept_temporary": false, "name_vac": "Программист"}