{"id": "43470153", "premium": false, "billing_type": {"id": "standard", "name": "Стандарт"}, "relations": [], "name": "Учитель-логопед", "insider_interview": null, "response_letter_required": false, "area": {"id": "78", "name": "Самара", "url": "https://api.hh.ru/areas/78?host=hh.ru"}, "salary": {"from": 5000, "to": 30000, "currency": "RUR", "gross": false}, "type": {"id": "open", "name": "Открытая"}, "address": {"city": "Самара", "street": "улица Карбышева", "building": "81", "description": null, "lat": 53.21118, "lng": 50.204874, "raw": "Самара, улица Карбышева, 81", "metro": null, "metro_stations": []}, "allow_messages": true, "site": {"id": "hh", "name": "hh.ru"}, "experience": {"id": "between1And3", "name": "От 1 года до 3 лет"}, "schedule": {"id": "fullDay", "name": "Полный день"}, "employment": {"id": "part", "name": "Частичная занятость"}, "department": null, "contacts": null, "description": "<p><strong>Обязанности:</strong></p> <ul> <li>проведение фронтальных и индивидуальных занятий по логопедии 2 раза в неделю</li> <li>ФФН, ОНР, Дизартрия</li> <li>диагностика речевых нарушений</li> <li>постановка звуков</li> </ul> <p><strong>Требования:</strong></p> <ul> <li>наличие педагогического образования ( специализация&quot;Логопедия&quot;)</li> <li>наличие оформленной медицинской книжки</li> </ul> <strong>Условия:</strong> <ul> <li>работа в филиалах по адресам: Карбышева, 81; Карла Маркса, 196; Первая просека, 10ж</li> <li>возможно совмещение с основной работой</li> </ul>", "branded_description": null, "vacancy_constructor_template": null, "key_skills": [], "accept_handicapped": false, "accept_kids": false, "archived": false, "response_url": null, "specializations": [{"id": "14.60", "name": "Гуманитарные науки", "profarea_id": "14", "profarea_name": "Наука, образование"}, {"id": "14.217", "name": "Преподавание", "profarea_id": "14", "profarea_name": "Наука, образование"}], "code": null, "hidden": false, "quick_responses_allowed": false, "driver_license_types": [], "accept_incomplete_resumes": false, "employer": "3305634", "published_at": "2021-03-30T16:10:10+0300", "created_at": "2021-03-30T16:10:10+0300", "negotiations_url": null, "suitable_resumes_url": null, "apply_alternate_url": "https://hh.ru/applicant/vacancy_response?vacancyId=43470153", "has_test": false, "test": null, "alternate_url": "https://hh.ru/vacancy/43470153", "working_days": [], "working_time_intervals": [], "working_time_modes": [], "accept_temporary": false, "name_vac": "Педагог"}