{"id": "43859365", "premium": false, "billing_type": {"id": "standard", "name": "Стандарт"}, "relations": [], "name": "Менеджер по продажам на рынке B2B", "insider_interview": null, "response_letter_required": false, "area": {"id": "212", "name": "Тольятти", "url": "https://api.hh.ru/areas/212?host=hh.ru"}, "salary": {"from": 50000, "to": null, "currency": "RUR", "gross": false}, "type": {"id": "open", "name": "Открытая"}, "address": {"city": "Тольятти", "street": "Южное шоссе", "building": "161к2/1", "description": null, "lat": 53.556952, "lng": 49.216485, "raw": "Тольятти, Южное шоссе, 161к2/1", "metro": null, "metro_stations": []}, "allow_messages": true, "site": {"id": "hh", "name": "hh.ru"}, "experience": {"id": "between1And3", "name": "От 1 года до 3 лет"}, "schedule": {"id": "fullDay", "name": "Полный день"}, "employment": {"id": "full", "name": "Полная занятость"}, "department": null, "contacts": null, "description": "<strong>Обязанности:</strong> <ul> <li><strong>Ведение и расширение клиентской базы</strong>: прямые продажи комплексных пакетов услуг компании на рынке B2B</li> <li><strong>Переговоры с первыми лицами компаний</strong> (по телефону, e-mail, деловые встречи в офисе), составление коммерческих предложений, заключение договоров.</li> <li> <p>помощь клиентам в выборе оптимального решения</p> </li> <li>Выполнение личного плана продаж</li> </ul> <strong>Требования:</strong> <ul> <li> <p>Наличие опыта ведения продаж от 1 года</p> </li> <li> <p>Готовность расти и развиваться как профессионал</p> </li> <li> <p>Стремление зарабатывать и ориентация на результат</p> </li> <li> <p>Инициативность.</p> </li> <li> <p>Ответственность</p> </li> <li> <p>Уверенный пользователь ПК</p> </li> <li> <p>Целеустремленность</p> </li> <li>Активная жизненная позиция</li> <li>Умение находить общий язык с любым человеком</li> <li>Желание построить карьеру в продажах</li> </ul> <strong>Условия:</strong> <ul> <li> <p>Заработная плата: оклад + % от продаж (нет потолка)</p> </li> <li> <p>Прогрессивная шкала дохода: чем больше продаж, тем выше %.</p> </li> <li> <p>Корпоративное обучение за счет компании: по продуктам и эффективной технике продаж</p> </li> <li> <p>Адаптационный период: поддержка по всем вопросам в работе</p> </li> <li> <p>Карьерный рост</p> </li> <li> <p>Безлимитная мобильная связь</p> </li> <li> <p>Дружный коллектив</p> </li> <li> <p>Корпоративные выезды на отдых</p> </li> <li> <p>Абонементы в фитнес-центр</p> </li> <li> <p>Участие в конференциях</p> </li> </ul> <p> </p>", "branded_description": null, "vacancy_constructor_template": null, "key_skills": [{"name": "Холодные продажи"}, {"name": "Прямые продажи"}, {"name": "Активные продажи"}, {"name": "B2B Продажи"}, {"name": "Заключение договоров"}, {"name": "Навыки переговоров"}, {"name": "проведение переговоров с первыми лицами компании"}, {"name": "Подготовка коммерческих предложений"}, {"name": "Грамотная речь"}], "accept_handicapped": false, "accept_kids": false, "archived": false, "response_url": null, "specializations": [{"id": "17.572", "name": "Тендеры", "profarea_id": "17", "profarea_name": "Продажи"}, {"id": "17.112", "name": "Компьютерные программы", "profarea_id": "17", "profarea_name": "Продажи"}, {"id": "17.242", "name": "Прямые продажи", "profarea_id": "17", "profarea_name": "Продажи"}, {"id": "17.149", "name": "Менеджер по работе с клиентами", "profarea_id": "17", "profarea_name": "Продажи"}, {"id": "17.183", "name": "Начальный уровень, Мало опыта", "profarea_id": "17", "profarea_name": "Продажи"}, {"id": "15.389", "name": "Продажи", "profarea_id": "15", "profarea_name": "Начало карьеры, студенты"}], "code": null, "hidden": false, "quick_responses_allowed": false, "driver_license_types": [], "accept_incomplete_resumes": false, "employer": "3926183", "published_at": "2021-04-13T22:50:10+0300", "created_at": "2021-04-13T22:50:10+0300", "negotiations_url": null, "suitable_resumes_url": null, "apply_alternate_url": "https://hh.ru/applicant/vacancy_response?vacancyId=43859365", "has_test": false, "test": null, "alternate_url": "https://hh.ru/vacancy/43859365", "working_days": [], "working_time_intervals": [], "working_time_modes": [], "accept_temporary": true, "name_vac": "Менеджер"}