{"id": "43887832", "premium": false, "billing_type": {"id": "standard", "name": "Стандарт"}, "relations": [], "name": "Начальник отдела информационно-коммуникационных технологий", "insider_interview": null, "response_letter_required": false, "area": {"id": "212", "name": "Тольятти", "url": "https://api.hh.ru/areas/212?host=hh.ru"}, "salary": {"from": 30000, "to": 30000, "currency": "RUR", "gross": true}, "type": {"id": "open", "name": "Открытая"}, "address": {"city": "Тольятти", "street": "проезд Строителей", "building": null, "description": null, "lat": 53.524097, "lng": 49.417312, "raw": "Тольятти, проезд Строителей", "metro": null, "metro_stations": []}, "allow_messages": true, "site": {"id": "hh", "name": "hh.ru"}, "experience": {"id": "between1And3", "name": "От 1 года до 3 лет"}, "schedule": {"id": "fullDay", "name": "Полный день"}, "employment": {"id": "full", "name": "Полная занятость"}, "department": null, "contacts": null, "description": "<p>Обязанности:</p> <p>— Осуществление руководства деятельностью отдела информационно-коммуникационных технологий (2 человека в непосредственном подчинении).</p> <p>— Организация взаимодействия с ИТ-персоналом аутсорсинговых компаний, в том числе составление технических заданий.<br />— Осуществление закупочной деятельности компьютерного оборудования, программного обеспечения, комплектующих (в рамках законов № 44-ФЗ, № 223-ФЗ).<br />— Техническая и консультационная поддержка пользователей программ «Система электронного документооборота Comsoft Docs», «СБИС», «АСУ РСО».<br />— Ведение и развитие официального сайта образовательного учреждения (CMS WordPress).</p> <p>— Ведение и наполнение личного кабинета бюджетного учреждения на сайте ГМУ (bus.gov.ru).</p> <p>— Обеспечение соблюдения сотрудниками закона № 152-ФЗ «О персональных данных».</p> <p> </p> <p>Требования: высшее образование (специалитет или магистратура) по направлениям подготовки «Прикладная информатика», «Прикладная математика и информатика», «Информационная безопасность», «Информатика и вычислительная техника», «Информационные системы и технологии», «Бизнес-информатика».</p> <p>Управленческий опыт в области ИТ более одного года, в управлении процессами разработки, управлении компонентами инфраструктуры или замещении менеджера по ресурсам ИТ более одного года</p> <p> </p> <p>Рекомендуется повышение квалификации по программам управления персоналом, управления бюджетом, управления ИТ, управления ресурсами (компонентами) ИТ</p> <p> </p> <p> </p> <p> </p> <p>Условия: рабочий день с 8-30 до 17-00. Обед с 13-13-30. Полный соцпакет.</p>", "branded_description": null, "vacancy_constructor_template": null, "key_skills": [{"name": "Организаторские навыки"}, {"name": "Деловая переписка"}, {"name": "Обучение персонала"}, {"name": "Пользователь ПК"}, {"name": "Cистемы управления базами данных"}, {"name": "Управленческое консультирование"}, {"name": "Умение работать в коллективе"}], "accept_handicapped": false, "accept_kids": false, "archived": false, "response_url": null, "specializations": [{"id": "1.110", "name": "Компьютерная безопасность", "profarea_id": "1", "profarea_name": "Информационные технологии, интернет, телеком"}], "code": "06.014-А-6", "hidden": false, "quick_responses_allowed": false, "driver_license_types": [], "accept_incomplete_resumes": false, "employer": "2069015", "published_at": "2021-04-14T15:58:51+0300", "created_at": "2021-04-14T15:58:51+0300", "negotiations_url": null, "suitable_resumes_url": null, "apply_alternate_url": "https://hh.ru/applicant/vacancy_response?vacancyId=43887832", "has_test": false, "test": null, "alternate_url": "https://hh.ru/vacancy/43887832", "working_days": [], "working_time_intervals": [], "working_time_modes": [], "accept_temporary": false, "name_vac": "Технолог"}